Skylark_Yolov8/__init__.py
Skylark_Yolov8-0.3.dist-info/METADATA
Skylark_Yolov8-0.3.dist-info/WHEEL
Skylark_Yolov8-0.3.dist-info/top_level.txt
Skylark_Yolov8-0.3.dist-info/RECORD
