Metadata-Version: 2.1
Name: Skylark-Yolov8
Version: 0.3
Summary: A video processing package
Author: Prem Varma
Author-email: prem.varma@skylarklabs.ai
Requires-Dist: opencv-python
Requires-Dist: ultralytics
